{
  "ui": {
    "headers": {
      "title": "Guidedog 요약",
      "tabTitle1": "전체 저장소",
      "tabTitle2": "단일 파일",
      "tabTitle3": "결과",
      "status": {
        "Perceivable": "인지 가능",
        "Operable": "운영 가능",
        "Understandable": "이해 가능",
        "Critical": "심각"
      }
    },
    "toolTips": {
      "WCAG": "이 그래프는 전체 프로젝트에서 발생한 위반 사항의 총량을 나타냅니다"
    },
    "errors": {
      "widthSmall": "계속하려면 사이드바를 확장하세요"
    },
    "links": {
      "seeAll": "모두 보기",
      "history": "기록"
    },
    "boxes": {
      "guideLinesViolations": {
        "title": "WCAG 가이드라인 위반",
        "suffix": "위반"
      },
      "issueList": {
        "title": "문제 목록",
        "linePrefix": "줄 ",
        "issuePillSuffix": " 문제"
      }
    },
    "text": {
      "lastUpdated": "마지막 업데이트"
    }
  }
}
